<?xml version="1.0" encoding="utf-8"?>
<ags:resources xmlns:ags="http://purl.org/agmes/1.1/" xmlns:dc="http://purl.org/dc/elements/1.1/" xmlns:agls="http://www.naa.gov.au/recordkeeping/gov_online/agls/1.2" xmlns:dcterms="http://purl.org/dc/terms/">
<ags:resource>
					<dc:title><![CDATA[]]></dc:title>
					<dc:creator>
					<ags:creatorPersonal><![CDATA[کریم پور, محمد حسن]]></ags:creatorPersonal>
<ags:creatorPersonal><![CDATA[مرادی, محراب]]></ags:creatorPersonal>
<ags:creatorPersonal><![CDATA[سلاطی, احسان]]></ags:creatorPersonal>

			</dc:creator>
			<dc:publisher>
				<ags:publisherName><![CDATA[Shahid Chamran University of Ahvaz]]></ags:publisherName>
			</dc:publisher>
			<dc:date><dcterms:dateIssued><![CDATA[2011]]></dcterms:dateIssued></dc:date>
			<dc:description>
				<ags:descriptionNotes><![CDATA[Includes references]]></ags:descriptionNotes>
				<dcterms:abstract><![CDATA[]]></dcterms:abstract>
			</dc:description>
            <dc:identifier scheme="dcterms:URI"><![CDATA[http://aag.scu.ac.ir/article_11529_b7730be51a93408b53026e63cf6f46bb.pdf]]></dc:identifier>
			<dc:identifier scheme="ags:DOI"><![CDATA[]]></dc:identifier>
			<dc:type><![CDATA[Journal Article]]></dc:type>
			<dc:format><dcterms:medium><![CDATA[text]]></dcterms:medium></dc:format>
			<dc:language><![CDATA[Persian]]></dc:language>
			<dc:source><![CDATA[http://aag.scu.ac.ir/]]></dc:source>
			<dc:source><![CDATA[Journal of Advanced Applied Geology]]></dc:source>
		</ags:resource>
<ags:resource>
					<dc:title><![CDATA[]]></dc:title>
					<dc:creator>
					<ags:creatorPersonal><![CDATA[محمدی لقب, حکیمه]]></ags:creatorPersonal>
<ags:creatorPersonal><![CDATA[تقی پور, نادر]]></ags:creatorPersonal>

			</dc:creator>
			<dc:publisher>
				<ags:publisherName><![CDATA[Shahid Chamran University of Ahvaz]]></ags:publisherName>
			</dc:publisher>
			<dc:date><dcterms:dateIssued><![CDATA[2011]]></dcterms:dateIssued></dc:date>
			<dc:description>
				<ags:descriptionNotes><![CDATA[Includes references]]></ags:descriptionNotes>
				<dcterms:abstract><![CDATA[]]></dcterms:abstract>
			</dc:description>
            <dc:identifier scheme="dcterms:URI"><![CDATA[http://aag.scu.ac.ir/article_11540_ca5a18daa9a996898b9d3dce158c16fd.pdf]]></dc:identifier>
			<dc:identifier scheme="ags:DOI"><![CDATA[]]></dc:identifier>
			<dc:type><![CDATA[Journal Article]]></dc:type>
			<dc:format><dcterms:medium><![CDATA[text]]></dcterms:medium></dc:format>
			<dc:language><![CDATA[Persian]]></dc:language>
			<dc:source><![CDATA[http://aag.scu.ac.ir/]]></dc:source>
			<dc:source><![CDATA[Journal of Advanced Applied Geology]]></dc:source>
		</ags:resource>
<ags:resource>
					<dc:title><![CDATA[]]></dc:title>
					<dc:creator>
					<ags:creatorPersonal><![CDATA[ناصری, حمیدرضا]]></ags:creatorPersonal>
<ags:creatorPersonal><![CDATA[علیجانی, فرشاد]]></ags:creatorPersonal>
<ags:creatorPersonal><![CDATA[نخعفی, محمد]]></ags:creatorPersonal>
<ags:creatorPersonal><![CDATA[محرابی نژاد, علی]]></ags:creatorPersonal>

			</dc:creator>
			<dc:publisher>
				<ags:publisherName><![CDATA[Shahid Chamran University of Ahvaz]]></ags:publisherName>
			</dc:publisher>
			<dc:date><dcterms:dateIssued><![CDATA[2011]]></dcterms:dateIssued></dc:date>
			<dc:description>
				<ags:descriptionNotes><![CDATA[Includes references]]></ags:descriptionNotes>
				<dcterms:abstract><![CDATA[]]></dcterms:abstract>
			</dc:description>
            <dc:identifier scheme="dcterms:URI"><![CDATA[http://aag.scu.ac.ir/article_11541_a8a2dbdebd38974e6a2ab8f1a0c1f559.pdf]]></dc:identifier>
			<dc:identifier scheme="ags:DOI"><![CDATA[]]></dc:identifier>
			<dc:type><![CDATA[Journal Article]]></dc:type>
			<dc:format><dcterms:medium><![CDATA[text]]></dcterms:medium></dc:format>
			<dc:language><![CDATA[Persian]]></dc:language>
			<dc:source><![CDATA[http://aag.scu.ac.ir/]]></dc:source>
			<dc:source><![CDATA[Journal of Advanced Applied Geology]]></dc:source>
		</ags:resource>
<ags:resource>
					<dc:title><![CDATA[]]></dc:title>
					<dc:creator>
					<ags:creatorPersonal><![CDATA[چرچی, عباس]]></ags:creatorPersonal>
<ags:creatorPersonal><![CDATA[خطیب, محمد مهدی]]></ags:creatorPersonal>
<ags:creatorPersonal><![CDATA[مظفر خواه, محمد]]></ags:creatorPersonal>
<ags:creatorPersonal><![CDATA[برجسته, آرش]]></ags:creatorPersonal>

			</dc:creator>
			<dc:publisher>
				<ags:publisherName><![CDATA[Shahid Chamran University of Ahvaz]]></ags:publisherName>
			</dc:publisher>
			<dc:date><dcterms:dateIssued><![CDATA[2011]]></dcterms:dateIssued></dc:date>
			<dc:description>
				<ags:descriptionNotes><![CDATA[Includes references]]></ags:descriptionNotes>
				<dcterms:abstract><![CDATA[]]></dcterms:abstract>
			</dc:description>
            <dc:identifier scheme="dcterms:URI"><![CDATA[http://aag.scu.ac.ir/article_11542_b92bb3e920d3a69401fca6e7d20266a5.pdf]]></dc:identifier>
			<dc:identifier scheme="ags:DOI"><![CDATA[]]></dc:identifier>
			<dc:type><![CDATA[Journal Article]]></dc:type>
			<dc:format><dcterms:medium><![CDATA[text]]></dcterms:medium></dc:format>
			<dc:language><![CDATA[Persian]]></dc:language>
			<dc:source><![CDATA[http://aag.scu.ac.ir/]]></dc:source>
			<dc:source><![CDATA[Journal of Advanced Applied Geology]]></dc:source>
		</ags:resource>
<ags:resource>
					<dc:title><![CDATA[]]></dc:title>
					<dc:creator>
					<ags:creatorPersonal><![CDATA[زارعی سهامیه, رضا]]></ags:creatorPersonal>
<ags:creatorPersonal><![CDATA[یوسفی یگانه, بیژن]]></ags:creatorPersonal>
<ags:creatorPersonal><![CDATA[زمانیان, حسن]]></ags:creatorPersonal>
<ags:creatorPersonal><![CDATA[معظمی گودرزی, فروغ]]></ags:creatorPersonal>

			</dc:creator>
			<dc:publisher>
				<ags:publisherName><![CDATA[Shahid Chamran University of Ahvaz]]></ags:publisherName>
			</dc:publisher>
			<dc:date><dcterms:dateIssued><![CDATA[2011]]></dcterms:dateIssued></dc:date>
			<dc:description>
				<ags:descriptionNotes><![CDATA[Includes references]]></ags:descriptionNotes>
				<dcterms:abstract><![CDATA[]]></dcterms:abstract>
			</dc:description>
            <dc:identifier scheme="dcterms:URI"><![CDATA[http://aag.scu.ac.ir/article_11543_3cca8138777410e63f977618b90a9b38.pdf]]></dc:identifier>
			<dc:identifier scheme="ags:DOI"><![CDATA[]]></dc:identifier>
			<dc:type><![CDATA[Journal Article]]></dc:type>
			<dc:format><dcterms:medium><![CDATA[text]]></dcterms:medium></dc:format>
			<dc:language><![CDATA[Persian]]></dc:language>
			<dc:source><![CDATA[http://aag.scu.ac.ir/]]></dc:source>
			<dc:source><![CDATA[Journal of Advanced Applied Geology]]></dc:source>
		</ags:resource>
<ags:resource>
					<dc:title><![CDATA[]]></dc:title>
					<dc:creator>
					<ags:creatorPersonal><![CDATA[فقیه, علی]]></ags:creatorPersonal>
<ags:creatorPersonal><![CDATA[سامانی, بابک]]></ags:creatorPersonal>
<ags:creatorPersonal><![CDATA[خبازی, سامان]]></ags:creatorPersonal>
<ags:creatorPersonal><![CDATA[روشنک, ریحانه]]></ags:creatorPersonal>

			</dc:creator>
			<dc:publisher>
				<ags:publisherName><![CDATA[Shahid Chamran University of Ahvaz]]></ags:publisherName>
			</dc:publisher>
			<dc:date><dcterms:dateIssued><![CDATA[2011]]></dcterms:dateIssued></dc:date>
			<dc:description>
				<ags:descriptionNotes><![CDATA[Includes references]]></ags:descriptionNotes>
				<dcterms:abstract><![CDATA[]]></dcterms:abstract>
			</dc:description>
            <dc:identifier scheme="dcterms:URI"><![CDATA[http://aag.scu.ac.ir/article_11544_c94cf33182e958d12b54231e6d2853b1.pdf]]></dc:identifier>
			<dc:identifier scheme="ags:DOI"><![CDATA[]]></dc:identifier>
			<dc:type><![CDATA[Journal Article]]></dc:type>
			<dc:format><dcterms:medium><![CDATA[text]]></dcterms:medium></dc:format>
			<dc:language><![CDATA[Persian]]></dc:language>
			<dc:source><![CDATA[http://aag.scu.ac.ir/]]></dc:source>
			<dc:source><![CDATA[Journal of Advanced Applied Geology]]></dc:source>
		</ags:resource>
<ags:resource>
					<dc:title><![CDATA[]]></dc:title>
					<dc:creator>
					<ags:creatorPersonal><![CDATA[رضایی, محسن]]></ags:creatorPersonal>
<ags:creatorPersonal><![CDATA[جمعه نیا, جلال]]></ags:creatorPersonal>
<ags:creatorPersonal><![CDATA[خدائی, کمال]]></ags:creatorPersonal>

			</dc:creator>
			<dc:publisher>
				<ags:publisherName><![CDATA[Shahid Chamran University of Ahvaz]]></ags:publisherName>
			</dc:publisher>
			<dc:date><dcterms:dateIssued><![CDATA[2011]]></dcterms:dateIssued></dc:date>
			<dc:description>
				<ags:descriptionNotes><![CDATA[Includes references]]></ags:descriptionNotes>
				<dcterms:abstract><![CDATA[]]></dcterms:abstract>
			</dc:description>
            <dc:identifier scheme="dcterms:URI"><![CDATA[http://aag.scu.ac.ir/article_11545_294f72691411d391834b4aac678a0aab.pdf]]></dc:identifier>
			<dc:identifier scheme="ags:DOI"><![CDATA[]]></dc:identifier>
			<dc:type><![CDATA[Journal Article]]></dc:type>
			<dc:format><dcterms:medium><![CDATA[text]]></dcterms:medium></dc:format>
			<dc:language><![CDATA[Persian]]></dc:language>
			<dc:source><![CDATA[http://aag.scu.ac.ir/]]></dc:source>
			<dc:source><![CDATA[Journal of Advanced Applied Geology]]></dc:source>
		</ags:resource>
<ags:resource>
					<dc:title><![CDATA[]]></dc:title>
					<dc:creator>
					<ags:creatorPersonal><![CDATA[مر, فرشید]]></ags:creatorPersonal>
<ags:creatorPersonal><![CDATA[اسدی, سینا]]></ags:creatorPersonal>
<ags:creatorPersonal><![CDATA[فتاحی, نسیم]]></ags:creatorPersonal>

			</dc:creator>
			<dc:publisher>
				<ags:publisherName><![CDATA[Shahid Chamran University of Ahvaz]]></ags:publisherName>
			</dc:publisher>
			<dc:date><dcterms:dateIssued><![CDATA[2011]]></dcterms:dateIssued></dc:date>
			<dc:description>
				<ags:descriptionNotes><![CDATA[Includes references]]></ags:descriptionNotes>
				<dcterms:abstract><![CDATA[]]></dcterms:abstract>
			</dc:description>
            <dc:identifier scheme="dcterms:URI"><![CDATA[http://aag.scu.ac.ir/article_11546_e955f060af82420e3b01fd1092bce371.pdf]]></dc:identifier>
			<dc:identifier scheme="ags:DOI"><![CDATA[]]></dc:identifier>
			<dc:type><![CDATA[Journal Article]]></dc:type>
			<dc:format><dcterms:medium><![CDATA[text]]></dcterms:medium></dc:format>
			<dc:language><![CDATA[Persian]]></dc:language>
			<dc:source><![CDATA[http://aag.scu.ac.ir/]]></dc:source>
			<dc:source><![CDATA[Journal of Advanced Applied Geology]]></dc:source>
		</ags:resource>
<ags:resource>
					<dc:title><![CDATA[]]></dc:title>
					<dc:creator>
					<ags:creatorPersonal><![CDATA[حسن زاده, مجمد مهدی]]></ags:creatorPersonal>
<ags:creatorPersonal><![CDATA[نوحه گر, احمد]]></ags:creatorPersonal>
<ags:creatorPersonal><![CDATA[حیدرزاده, مریم]]></ags:creatorPersonal>

			</dc:creator>
			<dc:publisher>
				<ags:publisherName><![CDATA[Shahid Chamran University of Ahvaz]]></ags:publisherName>
			</dc:publisher>
			<dc:date><dcterms:dateIssued><![CDATA[2011]]></dcterms:dateIssued></dc:date>
			<dc:description>
				<ags:descriptionNotes><![CDATA[Includes references]]></ags:descriptionNotes>
				<dcterms:abstract><![CDATA[]]></dcterms:abstract>
			</dc:description>
            <dc:identifier scheme="dcterms:URI"><![CDATA[http://aag.scu.ac.ir/article_11547_6425b5ce01e5d8872012b1ab184599d3.pdf]]></dc:identifier>
			<dc:identifier scheme="ags:DOI"><![CDATA[]]></dc:identifier>
			<dc:type><![CDATA[Journal Article]]></dc:type>
			<dc:format><dcterms:medium><![CDATA[text]]></dcterms:medium></dc:format>
			<dc:language><![CDATA[Persian]]></dc:language>
			<dc:source><![CDATA[http://aag.scu.ac.ir/]]></dc:source>
			<dc:source><![CDATA[Journal of Advanced Applied Geology]]></dc:source>
		</ags:resource>
<ags:resource>
					<dc:title><![CDATA[]]></dc:title>
					<dc:creator>
					<ags:creatorPersonal><![CDATA[فیروزی, محمدعلی]]></ags:creatorPersonal>
<ags:creatorPersonal><![CDATA[امانپور, سعید]]></ags:creatorPersonal>
<ags:creatorPersonal><![CDATA[محمدی, عباس]]></ags:creatorPersonal>

			</dc:creator>
			<dc:publisher>
				<ags:publisherName><![CDATA[Shahid Chamran University of Ahvaz]]></ags:publisherName>
			</dc:publisher>
			<dc:date><dcterms:dateIssued><![CDATA[2011]]></dcterms:dateIssued></dc:date>
			<dc:description>
				<ags:descriptionNotes><![CDATA[Includes references]]></ags:descriptionNotes>
				<dcterms:abstract><![CDATA[]]></dcterms:abstract>
			</dc:description>
            <dc:identifier scheme="dcterms:URI"><![CDATA[http://aag.scu.ac.ir/article_11548_0a4fb200223fa1925d20299b82f61dd1.pdf]]></dc:identifier>
			<dc:identifier scheme="ags:DOI"><![CDATA[]]></dc:identifier>
			<dc:type><![CDATA[Journal Article]]></dc:type>
			<dc:format><dcterms:medium><![CDATA[text]]></dcterms:medium></dc:format>
			<dc:language><![CDATA[Persian]]></dc:language>
			<dc:source><![CDATA[http://aag.scu.ac.ir/]]></dc:source>
			<dc:source><![CDATA[Journal of Advanced Applied Geology]]></dc:source>
		</ags:resource>

</ags:resources>