<?xml version="1.0" encoding="UTF-8"?>
<!DOCTYPE ArticleSet PUBLIC "-//NLM//DTD PubMed 2.7//EN" "https://dtd.nlm.nih.gov/ncbi/pubmed/in/PubMed.dtd">
<ArticleSet>
<Article>
<Journal>
				<PublisherName>انجمن زبان شناسی ایران</PublisherName>
				<JournalTitle>زبان و زبان‌شناسی</JournalTitle>
				<Issn></Issn>
				<Volume>7</Volume>
				<Issue>14</Issue>
				<PubDate PubStatus="epublish">
					<Year>2011</Year>
					<Month>09</Month>
					<Day>23</Day>
				</PubDate>
			</Journal>
<ArticleTitle>A semantic study of body-based compound verbs in Persian: A cognitive approach</ArticleTitle>
<VernacularTitle>بررسی معنایی افعال مرکبِ اندام‏بنیاد در زبان فارسی: رویکردی شناختی</VernacularTitle>
			<FirstPage>98</FirstPage>
			<LastPage>112</LastPage>
			<ELocationID EIdType="pii">1451</ELocationID>
			
			
			<Language>FA</Language>
<AuthorList>
<Author>
					<FirstName>راحله</FirstName>
					<LastName>گندمکار</LastName>
<Affiliation>دانشجوی دکترای زبان‌شناسی همگانی</Affiliation>

</Author>
</AuthorList>
				<PublicationType>Journal Article</PublicationType>
			<History>
				<PubDate PubStatus="received">
					<Year>2011</Year>
					<Month>05</Month>
					<Day>23</Day>
				</PubDate>
			</History>
		<Abstract>The present paper is an attempt to show the behavior of 176 body-based compound verbs in Persian, using a cognitive semantics framework, derived from formal linguistics in the 1970s. It focuses on ‘the image schema’. The findings show that the semantic core of a compound verb has the main role in forming the image schema of that verb. However, cognitive linguistics seems to lack absolute efficiency in explaining compound verbs semantically.</Abstract>
			<OtherAbstract Language="FA">رویی شناختییی در دهة 1970 جوانه زد، شامل چندین نظرییی برخوردارند. معنی‏شناسانِ شناختی، همچون لیی و مفاهیم را ازطرییریِ طرح‏واره‏های تصورییر میین تجسم ذهنی در ساخت‏های زبانیی‏شود. با بررسییاد در زبان فارسیی نگرش دبیرمقدم (1384) گردآوری شده‏اند، چنین به‌نظر مییییری طرح‏واره‏های تصوری قابل تأیید است، و در واقع، می‏توان عامل اصلییری طرح‏واره‏های تصوری را «هستة معنایییی‏شناسی شناختی در توجیه معنایی تمامی‌هم ازطریق به‌دست‌دادنِ طرح‏واره‏های تصورییی لازم و مطلوب برخوردار نیست.</OtherAbstract>
		<ObjectList>
			<Object Type="keyword">
			<Param Name="value">معنی‏شناسی</Param>
			</Object>
			<Object Type="keyword">
			<Param Name="value">زبان‏شناسی شناختی</Param>
			</Object>
			<Object Type="keyword">
			<Param Name="value">طرح‏وارة تصوری</Param>
			</Object>
			<Object Type="keyword">
			<Param Name="value">‌ فعل مرکب</Param>
			</Object>
			<Object Type="keyword">
			<Param Name="value">‌ اندام‏واژه</Param>
			</Object>
		</ObjectList>
<ArchiveCopySource DocType="pdf">http://lsi-linguistics.ihcs.ac.ir/article_1451_c13c846f877d92b74cc0762ce6df7893.pdf</ArchiveCopySource>
</Article>
</ArticleSet>
