<?xml version="1.0" encoding="UTF-8"?>
<!DOCTYPE ArticleSet PUBLIC "-//NLM//DTD PubMed 2.7//EN" "https://dtd.nlm.nih.gov/ncbi/pubmed/in/PubMed.dtd">
<ArticleSet>
<Article>
<Journal>
				<PublisherName>انجمن زمین شناسی مهندسی ایران</PublisherName>
				<JournalTitle>نشریه انجمن زمین شناسی مهندسی ایران</JournalTitle>
				<Issn>2228-5245</Issn>
				<Volume>6</Volume>
				<Issue>شماره 3 و 4</Issue>
				<PubDate PubStatus="epublish">
					<Year>2014</Year>
					<Month>02</Month>
					<Day>20</Day>
				</PubDate>
			</Journal>
<ArticleTitle>Estimation of uniaxial compressive strength of limestone marls from Abderaz formation by using physical properties</ArticleTitle>
<VernacularTitle>تخمین مقاومت تراکمی تک‌محوری آهک‌های مارنی سازند آبدراز با استفاده از خصوصیات فیزیکی</VernacularTitle>
			<FirstPage>89</FirstPage>
			<LastPage>97</LastPage>
			<ELocationID EIdType="pii">68337</ELocationID>
			
			
			<Language>FA</Language>
<AuthorList>
<Author>
					<FirstName>معصومه</FirstName>
					<LastName>خلیلی</LastName>
<Affiliation>دانشجوی دوره کارشناسی ارشد زمین‌شناسی مهندسی دانشگاه فردوسی مشهد</Affiliation>

</Author>
<Author>
					<FirstName>غلامرضا</FirstName>
					<LastName>لشکری پور</LastName>
<Affiliation>استاد گروه زمین شناسی مهندسی دانشگاه فردوسی</Affiliation>

</Author>
<Author>
					<FirstName>محمد</FirstName>
					<LastName>غفوری</LastName>
<Affiliation>دانشگاه فردوسی مشهد</Affiliation>

</Author>
<Author>
					<FirstName>محمد</FirstName>
					<LastName>خانه باد</LastName>
<Affiliation>استادیار گروه زمین‌شناسی دانشکده علوم پایه دانشگاه فردوسی مشهد</Affiliation>

</Author>
<Author>
					<FirstName>پوریا</FirstName>
					<LastName>دهقان</LastName>
<Affiliation>دانشجوی دوره دکتری زمین‌شناسی مهندسی پردیس دانشگاه فردوسی مشهد</Affiliation>

</Author>
</AuthorList>
				<PublicationType>Journal Article</PublicationType>
			<History>
				<PubDate PubStatus="received">
					<Year>2013</Year>
					<Month>06</Month>
					<Day>26</Day>
				</PubDate>
			</History>
		<Abstract>the purpose of this &lt;span style=&quot;text-decoration: underline;&quot;&gt;study&lt;/span&gt; is presenting and &lt;span style=&quot;text-decoration: underline;&quot;&gt;study&lt;/span&gt; of simple equations to estimate the uniaxial compressive strength of marly limestone of Abderaz formation. Many engineering structures such as dam, tunnel and road have been constructed on this formation in the northern part of Khorasan Razavi province. For &lt;span style=&quot;text-decoration: underline;&quot;&gt;determation &lt;/span&gt;physical parameters and uniaxial compressive strength of &lt;span style=&quot;text-decoration: underline;&quot;&gt;marly limestone&lt;/span&gt;, 39 samples according to the International Society of Rock Mechanics Standards &lt;span style=&quot;text-decoration: underline;&quot;&gt;(1981)&lt;/span&gt; of Abderaz formation were collected. Physical properties which determined &lt;span style=&quot;text-decoration: underline;&quot;&gt;including&lt;/span&gt; of porosity, density, water absorption. Results which obtained from the simple regression method, indicating a better relationship between density and uniaxial compressive strength in comparison with the other physical &lt;span style=&quot;text-decoration: underline;&quot;&gt;properties&lt;/span&gt;. The best multivariate correlation is obtained between uniaxial compressive strength with density and water absorption.</Abstract>
			<OtherAbstract Language="FA">هدف از این تحقیق ارائه و بررسی روابط ساده و چندمتغیره برای تخمین مقاومت فشاری نمونه‌هایی از سنگ آهک‌های مارنی سازند آبدراز است. بر روی این سازند پروژه‌های مهندسی زیادی مانند سد، تونل و جاده در شمال استان خراسان رضوی احداث شده است. برای این منظور برروی 39 نمونه سنگ آهک مارنی سازند آبدراز مطابق با استاندارد انجمن بین‌المللی مکانیک سنگ، آزمایش‌های مربوط به تعیین خصوصیات فیزیکی شامل تخلخل، دانسیته، جذب آب انجام شد و روابطی چند متغیره برای تخمین مقاومت فشاری به دست آمد. نتایج به دست آمده از روش رگرسیون ساده، نشان دهنده‌ی کارایی بهتر دانسیته نسبت به دیگر ویژگی‌های سنگ در تخمین مقاومت تراکمی تک‌محوری است. بهترین رابطه‌ی چندمتغیره نیز به ازای استفاده از متغیرهای مستقل دانسیته و جذب آب برای کل نمونه‌ها به دست آمد.</OtherAbstract>
		<ObjectList>
			<Object Type="keyword">
			<Param Name="value">خصوصیات فیزیکی</Param>
			</Object>
			<Object Type="keyword">
			<Param Name="value">مقاومت فشاری تک‌محوری</Param>
			</Object>
			<Object Type="keyword">
			<Param Name="value">آهک مارنی</Param>
			</Object>
			<Object Type="keyword">
			<Param Name="value">سازند آبدراز</Param>
			</Object>
		</ObjectList>
<ArchiveCopySource DocType="pdf">http://www.jiraeg.ir/article_68337_16cab7a9456033078b59c5c8e63ad711.pdf</ArchiveCopySource>
</Article>
</ArticleSet>
